MANIFEST.in
setup.py
ballade/__init__.py
ballade/config.py
ballade/run.py
ballade/server.py
ballade/startup.py
ballade/utils.py
ballade.egg-info/PKG-INFO
ballade.egg-info/SOURCES.txt
ballade.egg-info/dependency_links.txt
ballade.egg-info/entry_points.txt
ballade.egg-info/requires.txt
ballade.egg-info/top_level.txt
ballade/sample/.config/ballade/china_ip_list.txt
ballade/sample/.config/ballade/config.yaml
ballade/sample/.config/ballade/omega.conf