Metadata-Version: 1.1
Name: ballade
Version: 0.97.6
Summary: A light weight http proxy based on tornado and an upstream proxy switcher using SwitchyOmega rules
Home-page: https://github.com/holyshawn/ballade
Author: holyshawn
Author-email: holyshawn@outlook.com
License: https://opensource.org/licenses/MIT
Platform: UNKNOWN
Classifier: License :: OSI Approved :: MIT License
Classifier: Programming Language :: Python
Classifier: Programming Language :: Python :: 3.4
Classifier: Programming Language :: Python :: 3.5
Classifier: Topic :: Internet :: Proxy Servers
